conf/__init__.py
conf/config.py
conf/parameters.toml
arrow_wrangler/__init__.py
arrow_wrangler/data_manipulation.py
arrow_wrangler/data_tools.py
arrow_wrangler/data_validation.py
arrow_wrangler/excel_helper.py
arrow_wrangler-1.0.0.dist-info/METADATA
arrow_wrangler-1.0.0.dist-info/WHEEL
arrow_wrangler-1.0.0.dist-info/RECORD
