Metadata-Version: 2.4
Name: arrow-wrangler
Version: 1.0.0
Summary: Standardise data manipulation with pyarrow datasets
Author: William Lee
Requires-Python: >=3.12
Requires-Dist: commitizen>=4.4.1
Requires-Dist: dynaconf>=3.2.10
Requires-Dist: great-tables>=0.20.0
Requires-Dist: ibis-framework[duckdb,polars]>=11.0.0
Requires-Dist: ipykernel>=6.29.5
Requires-Dist: loguru>=0.7.3
Requires-Dist: nbclient>=0.10.2
Requires-Dist: nbformat>=5.10.4
Requires-Dist: orjson>=3.11.5
Requires-Dist: pandas>=2.3.3
Requires-Dist: pandera>=0.28.1
Requires-Dist: pins>=0.9.1
Requires-Dist: polars>=1.37.1
Requires-Dist: pytest-cov>=6.0.0
Requires-Dist: pytest>=8.3.5
Requires-Dist: quartodoc>=0.9.1
Requires-Dist: toml>=0.10.2
Requires-Dist: typer>=0.15.2
Requires-Dist: xlwings>=0.33.19
